{ "compressionlevel":-1,
 "height":24,
 "infinite":false,
 "layers":[
        {
         "data":[16, 47, 47, 47, 47, 47, 47, 47, 47, 47, 47, 47, 47, 47, 47, 47, 47, 47, 47, 17, 19, 19, 19, 19, 31, 5, 44, 44, 44, 44, 44, 44, 44, 6, 27, 27, 5, 44, 44, 44, 44, 44, 6, 46, 47, 17, 19, 19, 31, 28, 0, 0, 0, 0, 0, 0, 0, 43, 6, 5, 45, 0, 0, 0, 0, 0, 43, 44, 6, 46, 17, 19, 31, 28, 0, 0, 0, 0, 0, 0, 0, 0, 26, 28, 0, 0, 0, 0, 0, 0, 0, 0, 43, 6, 29, 19, 31, 28, 0, 0, 0, 0, 0, 0, 0, 0, 43, 8, 0, 0, 0, 0, 0, 0, 0, 0, 0, 26, 46, 17, 31, 28, 0, 0, 0, 0, 4, 0, 0, 0, 0, 21, 0, 0, 0, 0, 0, 0, 0, 0, 0, 43, 6, 29, 31, 22, 10, 10, 39, 53, 59, 0, 0, 0, 0, 38, 0, 0, 0, 0, 0, 0, 0, 0, 0, 0, 26, 29, 31, 27, 5, 44, 45, 0, 0, 0, 0, 0, 0, 0, 0, 0, 0, 0, 0, 0, 0, 0, 0, 0, 26, 29, 31, 5, 45, 0, 0, 0, 0, 0, 0, 0, 0, 0, 0, 0, 0, 0, 0, 0, 0, 0, 0, 0, 26, 29, 31, 28, 0, 0, 0, 0, 0, 0, 0, 0, 0, 52, 40, 11, 0, 0, 0, 0, 0, 0, 0, 9, 23, 29, 31, 28, 0, 0, 0, 0, 0, 0, 0, 0, 0, 0, 43, 44, 40, 10, 10, 10, 10, 10, 10, 23, 27, 29, 31, 28, 0, 0, 0, 0, 0, 0, 0, 0, 0, 0, 0, 0, 43, 44, 44, 6, 27, 27, 27, 27, 27, 29, 31, 28, 0, 0, 0, 0, 0, 0, 0, 0, 0, 0, 0, 0, 0, 0, 0, 43, 44, 44, 44, 6, 27, 29, 31, 28, 0, 0, 0, 0, 0, 0, 0, 0, 0, 0, 0, 0, 0, 0, 0, 0, 0, 0, 0, 43, 27, 29, 31, 65, 78, 78, 73, 61, 61, 62, 0, 0, 0, 0, 0, 0, 0, 0, 0, 0, 0, 0, 0, 0, 26, 29, 31, 27, 5, 44, 45, 0, 0, 0, 0, 0, 0, 0, 0, 0, 0, 0, 0, 0, 0, 0, 0, 0, 26, 29, 31, 5, 45, 0, 0, 0, 0, 0, 0, 0, 0, 0, 0, 0, 0, 0, 0, 0, 0, 0, 0, 0, 26, 29, 31, 28, 0, 0, 0, 0, 0, 0, 0, 0, 0, 0, 0, 0, 0, 0, 0, 0, 0, 0, 0, 0, 26, 29, 31, 28, 0, 0, 0, 0, 0, 0, 0, 0, 0, 0, 0, 0, 0, 0, 77, 78, 78, 78, 78, 78, 66, 29, 31, 28, 0, 0, 0, 0, 0, 0, 0, 0, 0, 0, 0, 0, 77, 78, 66, 12, 13, 13, 13, 13, 13, 34, 31, 28, 0, 0, 0, 0, 0, 0, 0, 0, 0, 77, 78, 78, 66, 12, 13, 34, 19, 19, 19, 19, 19, 19, 31, 28, 0, 0, 0, 0, 0, 0, 77, 78, 78, 66, 12, 13, 13, 34, 19, 19, 19, 19, 19, 19, 19, 19, 31, 65, 78, 78, 78, 78, 78, 78, 66, 12, 13, 13, 34, 19, 19, 19, 19, 19, 19, 19, 19, 19, 19, 19, 33, 13, 13, 13, 13, 13, 13, 13, 13, 34, 19, 19, 19, 19, 19, 19, 19, 19, 19, 19, 19, 19, 19, 19],
         "height":24,
         "id":1,
         "name":"ground",
         "opacity":1,
         "type":"tilelayer",
         "visible":true,
         "width":24,
         "x":0,
         "y":0
        }, 
        {
         "data":[0, 0, 0, 0, 0, 0, 0, 0, 0, 0, 0, 0, 0, 0, 0, 0, 0, 0, 0, 0, 0, 0, 0, 0, 0, 0, 0, 0, 0, 0, 0, 0, 0, 0, 0, 0, 0, 0, 0, 0, 0, 0, 0, 0, 0, 0, 0, 0, 0, 0, 0, 0, 0, 0, 0, 0, 0, 0, 0, 0, 0, 0, 0, 0, 0, 0, 0, 0, 0, 0, 0, 0, 0, 0, 0, 0, 0, 0, 0, 0, 0, 0, 0, 0, 0, 0, 0, 0, 0, 0, 0, 0, 0, 0, 0, 0, 0, 0, 0, 0, 0, 0, 84, 0, 0, 0, 0, 0, 0, 0, 0, 0, 0, 0, 0, 0, 0, 0, 0, 0, 0, 0, 0, 0, 0, 0, 0, 0, 0, 0, 0, 0, 0, 0, 0, 0, 0, 0, 0, 0, 0, 0, 0, 0, 0, 0, 0, 0, 0, 0, 0, 0, 0, 0, 0, 0, 0, 0, 0, 0, 0, 0, 0, 0, 0, 0, 0, 0, 0, 0, 0, 0, 0, 0, 0, 0, 0, 0, 0, 0, 0, 0, 0, 0, 0, 0, 0, 0, 0, 50, 0, 0, 0, 0, 0, 0, 0, 0, 0, 0, 0, 0, 0, 0, 0, 0, 0, 0, 0, 0, 0, 0, 0, 67, 0, 0, 0, 0, 0, 0, 0, 0, 0, 0, 0, 0, 0, 0, 0, 0, 84, 0, 0, 0, 0, 0, 85, 0, 0, 0, 0, 0, 0, 0, 0, 0, 0, 0, 0, 0, 0, 0, 0, 0, 0, 0, 0, 0, 0, 0, 0, 0, 0, 0, 0, 0, 0, 0, 0, 0, 0, 0, 0, 0, 0, 0, 0, 0, 0, 0, 0, 0, 0, 0, 0, 0, 0, 0, 0, 0, 0, 0, 0, 0, 0, 0, 0, 0, 0, 0, 0, 0, 0, 0, 0, 0, 0, 0, 0, 0, 0, 0, 0, 0, 0, 0, 0, 0, 0, 0, 0, 0, 0, 0, 0, 0, 0, 0, 0, 0, 0, 0, 0, 0, 0, 0, 0, 0, 0, 0, 0, 0, 0, 0, 0, 0, 0, 0, 0, 0, 0, 0, 0, 0, 0, 0, 0, 0, 0, 0, 0, 0, 0, 0, 0, 0, 0, 0, 0, 0, 0, 0, 0, 0, 0, 0, 0, 0, 0, 0, 0, 0, 0, 0, 0, 0, 0, 0, 0, 0, 0, 0, 0, 0, 0, 0, 0, 0, 0, 0, 0, 0, 0, 0, 0, 0, 0, 0, 0, 0, 0, 0, 0, 0, 0, 0, 0, 0, 0, 0, 0, 0, 50, 0, 0, 0, 0, 0, 0, 0, 0, 0, 0, 0, 0, 0, 0, 0, 0, 0, 0, 0, 0, 0, 0, 0, 67, 84, 0, 0, 0, 0, 0, 0, 0, 0, 0, 0, 0, 0, 0, 0, 0, 0, 0, 50, 51, 0, 0, 85, 0, 0, 0, 0, 0, 0, 0, 0, 0, 0, 0, 0, 0, 0, 0, 0, 0, 0, 85, 67, 68, 0, 0, 0, 0, 0, 0, 0, 0, 0, 0, 0, 0, 0, 0, 0, 0, 0, 0, 0, 0, 85, 0, 0, 0, 0, 0, 0, 0, 0, 0, 0, 0, 0, 0, 0, 0, 0, 0, 0, 0, 0, 0, 0, 0, 0, 0, 0, 0, 0, 0, 0, 0, 0, 0, 0, 0, 0, 0, 0, 0, 0, 0, 0, 0, 0, 0, 0, 0, 0, 0, 0, 0, 0, 0, 0, 0, 0, 0, 0, 0, 0, 0, 0, 0, 0],
         "height":24,
         "id":3,
         "name":"obstacles",
         "opacity":1,
         "type":"tilelayer",
         "visible":true,
         "width":24,
         "x":0,
         "y":0
        }, 
        {
         "draworder":"topdown",
         "id":2,
         "name":"objects",
         "objects":[
                {
                 "height":0,
                 "id":7,
                 "name":"playerSpawn",
                 "rotation":0,
                 "type":"",
                 "visible":true,
                 "width":0,
                 "x":109.996618956385,
                 "y":399.413952439987
                }, 
                {
                 "height":0,
                 "id":9,
                 "name":"enemySpawn",
                 "rotation":0,
                 "type":"",
                 "visible":true,
                 "width":0,
                 "x":494.98478530373,
                 "y":269.581877606221
                }, 
                {
                 "height":29.7531838160712,
                 "id":10,
                 "name":"spike",
                 "rotation":0,
                 "type":"",
                 "visible":true,
                 "width":29.7531838160712,
                 "x":192.043277358278,
                 "y":129.832074833765
                }, 
                {
                 "height":27.0483489237011,
                 "id":11,
                 "name":"spike",
                 "rotation":0,
                 "type":"",
                 "visible":true,
                 "width":27.9499605544912,
                 "x":448.100980502648,
                 "y":292.122168375972
                }, 
                {
                 "height":27.9499605544912,
                 "id":12,
                 "name":"spike",
                 "rotation":0,
                 "type":"",
                 "visible":true,
                 "width":27.048348923701,
                 "x":641.045869491717,
                 "y":291.220556745182
                }, 
                {
                 "height":61.3095908937225,
                 "id":13,
                 "name":"spike",
                 "rotation":0,
                 "type":"",
                 "visible":true,
                 "width":27.0483489237012,
                 "x":672.602276569368,
                 "y":226.304519328299
                }, 
                {
                 "height":60.4079792629326,
                 "id":14,
                 "name":"spike",
                 "rotation":0,
                 "type":"",
                 "visible":true,
                 "width":28.8515721852812,
                 "x":449.002592133439,
                 "y":545.475036627972
                }, 
                {
                 "height":27.9499605544912,
                 "id":15,
                 "name":"spike",
                 "rotation":0,
                 "type":"",
                 "visible":true,
                 "width":29.7531838160712,
                 "x":479.6573875803,
                 "y":577.933055336414
                }, 
                {
                 "height":27.9499605544911,
                 "id":16,
                 "name":"spike",
                 "rotation":0,
                 "type":"",
                 "visible":true,
                 "width":27.0483489237012,
                 "x":417.446185055787,
                 "y":610.391074044855
                }, 
                {
                 "height":59.5063676321424,
                 "id":17,
                 "name":"spike",
                 "rotation":0,
                 "type":"",
                 "visible":true,
                 "width":58.6047560013524,
                 "x":290.318945114392,
                 "y":610.391074044855
                }, 
                {
                 "height":27.0483489237012,
                 "id":18,
                 "name":"spike",
                 "rotation":0,
                 "type":"",
                 "visible":true,
                 "width":25.245125662121,
                 "x":258.762538036741,
                 "y":642.849092753297
                }, 
                {
                 "height":27.9499605544911,
                 "id":19,
                 "name":"spike",
                 "rotation":0,
                 "type":"",
                 "visible":true,
                 "width":27.0483489237011,
                 "x":226.304519328299,
                 "y":675.307111461738
                }, 
                {
                 "height":0,
                 "id":20,
                 "name":"star",
                 "rotation":0,
                 "type":"",
                 "visible":true,
                 "width":0,
                 "x":368.759156993125,
                 "y":256.057703144371
                }, 
                {
                 "height":0,
                 "id":21,
                 "name":"cheese",
                 "rotation":0,
                 "type":"",
                 "visible":true,
                 "width":0,
                 "x":191.141665727488,
                 "y":335.399526653894
                }, 
                {
                 "height":0,
                 "id":22,
                 "name":"cheese",
                 "rotation":0,
                 "type":"",
                 "visible":true,
                 "width":0,
                 "x":226.304519328299,
                 "y":316.465682407303
                }, 
                {
                 "height":0,
                 "id":23,
                 "name":"cheese",
                 "rotation":0,
                 "type":"",
                 "visible":true,
                 "width":0,
                 "x":107.291784064014,
                 "y":675.307111461738
                }, 
                {
                 "height":0,
                 "id":24,
                 "name":"cheese",
                 "rotation":0,
                 "type":"",
                 "visible":true,
                 "width":0,
                 "x":151.470753972726,
                 "y":678.913557984898
                }, 
                {
                 "height":0,
                 "id":25,
                 "name":"cheese",
                 "rotation":0,
                 "type":"",
                 "visible":true,
                 "width":0,
                 "x":578.834666967204,
                 "y":541.868590104812
                }, 
                {
                 "height":0,
                 "id":26,
                 "name":"cheese",
                 "rotation":0,
                 "type":"",
                 "visible":true,
                 "width":0,
                 "x":538.262143581652,
                 "y":185.731995942748
                }, 
                {
                 "height":0,
                 "id":27,
                 "name":"cheese",
                 "rotation":0,
                 "type":"",
                 "visible":true,
                 "width":0,
                 "x":569.818550659304,
                 "y":188.436830835118
                }, 
                {
                 "height":0,
                 "id":28,
                 "name":"cheese",
                 "rotation":0,
                 "type":"",
                 "visible":true,
                 "width":0,
                 "x":553.589541305083,
                 "y":219.993237912769
                }, 
                {
                 "height":0,
                 "id":29,
                 "name":"cheese",
                 "rotation":0,
                 "type":"",
                 "visible":true,
                 "width":0,
                 "x":137.946579510876,
                 "y":143.356249295616
                }, 
                {
                 "height":0,
                 "id":30,
                 "name":"cheese",
                 "rotation":0,
                 "type":"",
                 "visible":true,
                 "width":0,
                 "x":156.880423757466,
                 "y":106.390172433224
                }, 
                {
                 "height":0,
                 "id":31,
                 "name":"cheese",
                 "rotation":0,
                 "type":"",
                 "visible":true,
                 "width":0,
                 "x":397.610729178406,
                 "y":245.23836357489
                }, 
                {
                 "height":0,
                 "id":32,
                 "name":"butter",
                 "rotation":0,
                 "type":"",
                 "visible":true,
                 "width":0,
                 "x":222.698072805139,
                 "y":354.333370900485
                }, 
                {
                 "height":0,
                 "id":33,
                 "name":"butter",
                 "rotation":0,
                 "type":"",
                 "visible":true,
                 "width":0,
                 "x":193.846500619858,
                 "y":290.318945114392
                }, 
                {
                 "height":0,
                 "id":34,
                 "name":"butter",
                 "rotation":0,
                 "type":"",
                 "visible":true,
                 "width":0,
                 "x":412.036515271047,
                 "y":164.093316803787
                }, 
                {
                 "height":0,
                 "id":35,
                 "name":"butter",
                 "rotation":0,
                 "type":"",
                 "visible":true,
                 "width":0,
                 "x":603.178180998535,
                 "y":227.206130959089
                }, 
                {
                 "height":0,
                 "id":36,
                 "name":"butter",
                 "rotation":0,
                 "type":"",
                 "visible":true,
                 "width":0,
                 "x":536.458920320072,
                 "y":133.438521356926
                }, 
                {
                 "height":0,
                 "id":37,
                 "name":"butter",
                 "rotation":0,
                 "type":"",
                 "visible":true,
                 "width":0,
                 "x":163.191705172997,
                 "y":167.699763326947
                }, 
                {
                 "height":0,
                 "id":38,
                 "name":"butter",
                 "rotation":0,
                 "type":"",
                 "visible":true,
                 "width":0,
                 "x":146.962695818776,
                 "y":554.491152935873
                }, 
                {
                 "height":0,
                 "id":39,
                 "name":"butter",
                 "rotation":0,
                 "type":"",
                 "visible":true,
                 "width":0,
                 "x":116.307900371915,
                 "y":575.228220444044
                }, 
                {
                 "height":0,
                 "id":40,
                 "name":"butter",
                 "rotation":0,
                 "type":"",
                 "visible":true,
                 "width":0,
                 "x":186.633607573538,
                 "y":580.637890228784
                }, 
                {
                 "height":0,
                 "id":41,
                 "name":"butter",
                 "rotation":0,
                 "type":"",
                 "visible":true,
                 "width":0,
                 "x":578.834666967204,
                 "y":480.55899921109
                }, 
                {
                 "height":0,
                 "id":42,
                 "name":"butter",
                 "rotation":0,
                 "type":"",
                 "visible":true,
                 "width":0,
                 "x":625.718471768286,
                 "y":470.641271272399
                }, 
                {
                 "height":0,
                 "id":43,
                 "name":"butter",
                 "rotation":0,
                 "type":"",
                 "visible":true,
                 "width":0,
                 "x":388.594612870506,
                 "y":558.999211089823
                }, 
                {
                 "height":0,
                 "id":44,
                 "name":"butter",
                 "rotation":0,
                 "type":"",
                 "visible":true,
                 "width":0,
                 "x":377.775273301026,
                 "y":537.360531950862
                }, 
                {
                 "height":0,
                 "id":46,
                 "name":"star",
                 "rotation":0,
                 "type":"",
                 "visible":true,
                 "width":0,
                 "x":511.213794657951,
                 "y":161.388481911417
                }, 
                {
                 "height":0,
                 "id":47,
                 "name":"star",
                 "rotation":0,
                 "type":"",
                 "visible":true,
                 "width":0,
                 "x":120.815958525865,
                 "y":109.996618956385
                }, 
                {
                 "height":0,
                 "id":48,
                 "name":"star",
                 "rotation":0,
                 "type":"",
                 "visible":true,
                 "width":0,
                 "x":138.848191141666,
                 "y":613.095908937225
                }, 
                {
                 "height":0,
                 "id":49,
                 "name":"star",
                 "rotation":0,
                 "type":"",
                 "visible":true,
                 "width":0,
                 "x":615.800743829595,
                 "y":496.788008565311
                }, 
                {
                 "height":0,
                 "id":50,
                 "name":"enemySpawn",
                 "rotation":0,
                 "type":"",
                 "visible":true,
                 "width":0,
                 "x":84.7514932942635,
                 "y":143.356249295616
                }],
         "opacity":1,
         "type":"objectgroup",
         "visible":true,
         "x":0,
         "y":0
        }],
 "nextlayerid":4,
 "nextobjectid":51,
 "orientation":"orthogonal",
 "renderorder":"right-down",
 "tiledversion":"1.7.2",
 "tileheight":32,
 "tilesets":[
        {
         "columns":17,
         "firstgid":1,
         "image":"..\/assets\/ForestTilesetNew.png",
         "imageheight":160,
         "imagewidth":544,
         "margin":0,
         "name":"ForestTilesetNew",
         "spacing":0,
         "tilecount":85,
         "tileheight":32,
         "tiles":[
                {
                 "id":0,
                 "properties":[
                        {
                         "name":"collides",
                         "type":"bool",
                         "value":true
                        }]
                }, 
                {
                 "id":1,
                 "properties":[
                        {
                         "name":"collides",
                         "type":"bool",
                         "value":true
                        }]
                }, 
                {
                 "id":2,
                 "properties":[
                        {
                         "name":"collides",
                         "type":"bool",
                         "value":true
                        }]
                }, 
                {
                 "id":3,
                 "properties":[
                        {
                         "name":"collides",
                         "type":"bool",
                         "value":true
                        }]
                }, 
                {
                 "id":4,
                 "properties":[
                        {
                         "name":"collides",
                         "type":"bool",
                         "value":true
                        }]
                }, 
                {
                 "id":5,
                 "properties":[
                        {
                         "name":"collides",
                         "type":"bool",
                         "value":true
                        }]
                }, 
                {
                 "id":6,
                 "properties":[
                        {
                         "name":"collides",
                         "type":"bool",
                         "value":true
                        }]
                }, 
                {
                 "id":7,
                 "properties":[
                        {
                         "name":"collides",
                         "type":"bool",
                         "value":true
                        }]
                }, 
                {
                 "id":8,
                 "properties":[
                        {
                         "name":"collides",
                         "type":"bool",
                         "value":true
                        }]
                }, 
                {
                 "id":9,
                 "properties":[
                        {
                         "name":"collides",
                         "type":"bool",
                         "value":true
                        }]
                }, 
                {
                 "id":10,
                 "properties":[
                        {
                         "name":"collides",
                         "type":"bool",
                         "value":true
                        }]
                }, 
                {
                 "id":11,
                 "properties":[
                        {
                         "name":"collides",
                         "type":"bool",
                         "value":false
                        }]
                }, 
                {
                 "id":12,
                 "properties":[
                        {
                         "name":"collides",
                         "type":"bool",
                         "value":false
                        }]
                }, 
                {
                 "id":13,
                 "properties":[
                        {
                         "name":"collides",
                         "type":"bool",
                         "value":false
                        }]
                }, 
                {
                 "id":14,
                 "properties":[
                        {
                         "name":"collides",
                         "type":"bool",
                         "value":true
                        }]
                }, 
                {
                 "id":15,
                 "properties":[
                        {
                         "name":"collides",
                         "type":"bool",
                         "value":false
                        }]
                }, 
                {
                 "id":16,
                 "properties":[
                        {
                         "name":"collides",
                         "type":"bool",
                         "value":false
                        }]
                }, 
                {
                 "id":17,
                 "properties":[
                        {
                         "name":"collides",
                         "type":"bool",
                         "value":true
                        }]
                }, 
                {
                 "id":18,
                 "properties":[
                        {
                         "name":"collides",
                         "type":"bool",
                         "value":false
                        }]
                }, 
                {
                 "id":19,
                 "properties":[
                        {
                         "name":"collides",
                         "type":"bool",
                         "value":true
                        }]
                }, 
                {
                 "id":20,
                 "properties":[
                        {
                         "name":"collides",
                         "type":"bool",
                         "value":true
                        }]
                }, 
                {
                 "id":21,
                 "properties":[
                        {
                         "name":"collides",
                         "type":"bool",
                         "value":true
                        }]
                }, 
                {
                 "id":22,
                 "properties":[
                        {
                         "name":"collides",
                         "type":"bool",
                         "value":true
                        }]
                }, 
                {
                 "id":23,
                 "properties":[
                        {
                         "name":"collides",
                         "type":"bool",
                         "value":true
                        }]
                }, 
                {
                 "id":24,
                 "properties":[
                        {
                         "name":"collides",
                         "type":"bool",
                         "value":true
                        }]
                }, 
                {
                 "id":25,
                 "properties":[
                        {
                         "name":"collides",
                         "type":"bool",
                         "value":true
                        }]
                }, 
                {
                 "id":26,
                 "properties":[
                        {
                         "name":"collides",
                         "type":"bool",
                         "value":false
                        }]
                }, 
                {
                 "id":27,
                 "properties":[
                        {
                         "name":"collides",
                         "type":"bool",
                         "value":true
                        }]
                }, 
                {
                 "id":28,
                 "properties":[
                        {
                         "name":"collides",
                         "type":"bool",
                         "value":false
                        }]
                }, 
                {
                 "id":29,
                 "properties":[
                        {
                         "name":"collides",
                         "type":"bool",
                         "value":false
                        }]
                }, 
                {
                 "id":30,
                 "properties":[
                        {
                         "name":"collides",
                         "type":"bool",
                         "value":false
                        }]
                }, 
                {
                 "id":31,
                 "properties":[
                        {
                         "name":"collides",
                         "type":"bool",
                         "value":false
                        }]
                }, 
                {
                 "id":32,
                 "properties":[
                        {
                         "name":"collides",
                         "type":"bool",
                         "value":false
                        }]
                }, 
                {
                 "id":33,
                 "properties":[
                        {
                         "name":"collides",
                         "type":"bool",
                         "value":false
                        }]
                }, 
                {
                 "id":34,
                 "properties":[
                        {
                         "name":"collides",
                         "type":"bool",
                         "value":true
                        }]
                }, 
                {
                 "id":35,
                 "properties":[
                        {
                         "name":"collides",
                         "type":"bool",
                         "value":true
                        }]
                }, 
                {
                 "id":36,
                 "properties":[
                        {
                         "name":"collides",
                         "type":"bool",
                         "value":true
                        }]
                }, 
                {
                 "id":37,
                 "properties":[
                        {
                         "name":"collides",
                         "type":"bool",
                         "value":true
                        }]
                }, 
                {
                 "id":38,
                 "properties":[
                        {
                         "name":"collides",
                         "type":"bool",
                         "value":true
                        }]
                }, 
                {
                 "id":39,
                 "properties":[
                        {
                         "name":"collides",
                         "type":"bool",
                         "value":true
                        }]
                }, 
                {
                 "id":40,
                 "properties":[
                        {
                         "name":"collides",
                         "type":"bool",
                         "value":true
                        }]
                }, 
                {
                 "id":41,
                 "properties":[
                        {
                         "name":"collides",
                         "type":"bool",
                         "value":true
                        }]
                }, 
                {
                 "id":42,
                 "properties":[
                        {
                         "name":"collides",
                         "type":"bool",
                         "value":true
                        }]
                }, 
                {
                 "id":43,
                 "properties":[
                        {
                         "name":"collides",
                         "type":"bool",
                         "value":true
                        }]
                }, 
                {
                 "id":44,
                 "properties":[
                        {
                         "name":"collides",
                         "type":"bool",
                         "value":true
                        }]
                }, 
                {
                 "id":45,
                 "properties":[
                        {
                         "name":"collides",
                         "type":"bool",
                         "value":false
                        }]
                }, 
                {
                 "id":46,
                 "properties":[
                        {
                         "name":"collides",
                         "type":"bool",
                         "value":false
                        }]
                }, 
                {
                 "id":47,
                 "properties":[
                        {
                         "name":"collides",
                         "type":"bool",
                         "value":false
                        }]
                }, 
                {
                 "id":48,
                 "properties":[
                        {
                         "name":"collides",
                         "type":"bool",
                         "value":false
                        }]
                }, 
                {
                 "id":49,
                 "properties":[
                        {
                         "name":"collides",
                         "type":"bool",
                         "value":false
                        }]
                }, 
                {
                 "id":50,
                 "properties":[
                        {
                         "name":"collides",
                         "type":"bool",
                         "value":false
                        }]
                }, 
                {
                 "id":51,
                 "properties":[
                        {
                         "name":"collides",
                         "type":"bool",
                         "value":true
                        }]
                }, 
                {
                 "id":52,
                 "properties":[
                        {
                         "name":"collides",
                         "type":"bool",
                         "value":true
                        }]
                }, 
                {
                 "id":53,
                 "properties":[
                        {
                         "name":"collides",
                         "type":"bool",
                         "value":true
                        }]
                }, 
                {
                 "id":54,
                 "properties":[
                        {
                         "name":"collides",
                         "type":"bool",
                         "value":true
                        }]
                }, 
                {
                 "id":55,
                 "properties":[
                        {
                         "name":"collides",
                         "type":"bool",
                         "value":true
                        }]
                }, 
                {
                 "id":56,
                 "properties":[
                        {
                         "name":"collides",
                         "type":"bool",
                         "value":true
                        }]
                }, 
                {
                 "id":57,
                 "properties":[
                        {
                         "name":"collides",
                         "type":"bool",
                         "value":true
                        }]
                }, 
                {
                 "id":58,
                 "properties":[
                        {
                         "name":"collides",
                         "type":"bool",
                         "value":true
                        }]
                }, 
                {
                 "id":59,
                 "properties":[
                        {
                         "name":"collides",
                         "type":"bool",
                         "value":true
                        }]
                }, 
                {
                 "id":60,
                 "properties":[
                        {
                         "name":"collides",
                         "type":"bool",
                         "value":true
                        }]
                }, 
                {
                 "id":61,
                 "properties":[
                        {
                         "name":"collides",
                         "type":"bool",
                         "value":true
                        }]
                }, 
                {
                 "id":62,
                 "properties":[
                        {
                         "name":"collides",
                         "type":"bool",
                         "value":true
                        }]
                }, 
                {
                 "id":63,
                 "properties":[
                        {
                         "name":"collides",
                         "type":"bool",
                         "value":true
                        }]
                }, 
                {
                 "id":64,
                 "properties":[
                        {
                         "name":"collides",
                         "type":"bool",
                         "value":true
                        }]
                }, 
                {
                 "id":65,
                 "properties":[
                        {
                         "name":"collides",
                         "type":"bool",
                         "value":true
                        }]
                }, 
                {
                 "id":66,
                 "properties":[
                        {
                         "name":"collides",
                         "type":"bool",
                         "value":false
                        }]
                }, 
                {
                 "id":67,
                 "properties":[
                        {
                         "name":"collides",
                         "type":"bool",
                         "value":false
                        }]
                }, 
                {
                 "id":68,
                 "properties":[
                        {
                         "name":"collides",
                         "type":"bool",
                         "value":true
                        }]
                }, 
                {
                 "id":69,
                 "properties":[
                        {
                         "name":"collides",
                         "type":"bool",
                         "value":true
                        }]
                }, 
                {
                 "id":70,
                 "properties":[
                        {
                         "name":"collides",
                         "type":"bool",
                         "value":true
                        }]
                }, 
                {
                 "id":71,
                 "properties":[
                        {
                         "name":"collides",
                         "type":"bool",
                         "value":true
                        }]
                }, 
                {
                 "id":72,
                 "properties":[
                        {
                         "name":"collides",
                         "type":"bool",
                         "value":true
                        }]
                }, 
                {
                 "id":73,
                 "properties":[
                        {
                         "name":"collides",
                         "type":"bool",
                         "value":true
                        }]
                }, 
                {
                 "id":74,
                 "properties":[
                        {
                         "name":"collides",
                         "type":"bool",
                         "value":true
                        }]
                }, 
                {
                 "id":75,
                 "properties":[
                        {
                         "name":"collides",
                         "type":"bool",
                         "value":true
                        }]
                }, 
                {
                 "id":76,
                 "properties":[
                        {
                         "name":"collides",
                         "type":"bool",
                         "value":true
                        }]
                }, 
                {
                 "id":77,
                 "properties":[
                        {
                         "name":"collides",
                         "type":"bool",
                         "value":true
                        }]
                }, 
                {
                 "id":78,
                 "properties":[
                        {
                         "name":"collides",
                         "type":"bool",
                         "value":true
                        }]
                }, 
                {
                 "id":79,
                 "properties":[
                        {
                         "name":"collides",
                         "type":"bool",
                         "value":true
                        }]
                }, 
                {
                 "id":80,
                 "properties":[
                        {
                         "name":"collides",
                         "type":"bool",
                         "value":true
                        }]
                }, 
                {
                 "id":81,
                 "properties":[
                        {
                         "name":"collides",
                         "type":"bool",
                         "value":true
                        }]
                }, 
                {
                 "id":82,
                 "properties":[
                        {
                         "name":"collides",
                         "type":"bool",
                         "value":true
                        }]
                }, 
                {
                 "id":83,
                 "properties":[
                        {
                         "name":"collides",
                         "type":"bool",
                         "value":false
                        }]
                }, 
                {
                 "id":84,
                 "properties":[
                        {
                         "name":"collides",
                         "type":"bool",
                         "value":false
                        }]
                }],
         "tilewidth":32
        }],
 "tilewidth":32,
 "type":"map",
 "version":"1.6",
 "width":24
}